libraries/__init__.py
libraries/analyze_correlations.py
libraries/analyze_descriptors.py
libraries/common_library.py
libraries/identify_diffusion.py
tests/__init__.py
tests/test_DIE.py
tests/test_MDR.py
tests/test_SPR.py
cibran-0.0.1.dist-info/LICENSE
cibran-0.0.1.dist-info/METADATA
cibran-0.0.1.dist-info/WHEEL
cibran-0.0.1.dist-info/top_level.txt
cibran-0.0.1.dist-info/RECORD
