Metadata-Version: 2.1
Name: cibran
Version: 0.0.1
Summary: Identification and analysis of ion-hopping events in solid state electrolytes.
Home-page: https://github.com/IonRepo/IonDiff
Author: Cibrán López Álvarez
Author-email: cibran.lopez@upc.edu
Classifier: Programming Language :: Python :: 3
Classifier: License :: OSI Approved :: MIT License
Classifier: Operating System :: OS Independent
License-File: LICENSE
